slumber/__init__.py
slumber/exceptions.py
slumber/serialize.py
slumber/utils.py
slumber-0.7.1.dist-info/DESCRIPTION.rst
slumber-0.7.1.dist-info/METADATA
slumber-0.7.1.dist-info/metadata.json
slumber-0.7.1.dist-info/RECORD
slumber-0.7.1.dist-info/top_level.txt
slumber-0.7.1.dist-info/WHEEL
