Metadata-Version: 1.0
Name: slumber
Version: 0.7.1
Summary: A library that makes consuming a REST API easier and more convenient
Home-page: http://github.com/samgiles/slumber
Author: Samuel Giles
Author-email: sam.e.giles@gmail.com
License: UNKNOWN
Platform: UNKNOWN
